MANIFEST.in
setup.py
XdbSearchIP/__init__.py
XdbSearchIP/bench_test.py
XdbSearchIP/iptest.py
XdbSearchIP/search_test.py
XdbSearchIP/xdbSearcher.py
XdbSearchIP.egg-info/PKG-INFO
XdbSearchIP.egg-info/SOURCES.txt
XdbSearchIP.egg-info/dependency_links.txt
XdbSearchIP.egg-info/top_level.txt
XdbSearchIP/data/.DS_Store
XdbSearchIP/data/ip2region.xdb