Metadata-Version: 2.1
Name: XdbSearchIP
Version: 1.0.1
Summary: ip2region查询Python版，数据来源https://github.com/lionsoul2014/ip2region，代码来源https://github.com/luckydog6132，本作者仅做封装使用。
Home-page: https://github.com/lionsoul2014/ip2region
Author: @道长
Author-email: ctrlf4@yeah.net
License: Apache License 2.0
Classifier: Programming Language :: Python :: 3
Classifier: License :: OSI Approved :: MIT License
Classifier: Operating System :: OS Independent
Requires-Python: >=3.5
